bandlimit/__init__.pxd
bandlimit/constants.pxd
bandlimit/coreMath.pxd
bandlimit/gaussian.c
bandlimit/gaussian.cpython-311-x86_64-linux-gnu.so
bandlimit/gaussian.pyx
bandlimit/system.pxi
bandlimit-1.2.4.dist-info/METADATA
bandlimit-1.2.4.dist-info/WHEEL
bandlimit-1.2.4.dist-info/top_level.txt
bandlimit-1.2.4.dist-info/RECORD
bandlimit-1.2.4.dist-info/licenses/LICENSE.txt
