Metadata-Version: 2.4
Name: bandlimit
Version: 1.2.4
Summary: Gaussians and plane waves playing well together
Author-email: Jonathan Jerke <jonathan@quantumgalaxies.org>
License-Expression: MIT
Project-URL: Homepage, https://sopy.quantumgalaxies.org
Project-URL: Issues, https://github.com/quantumgalaxies/sopy/issues
Classifier: Programming Language :: Python :: 3
Classifier: Operating System :: OS Independent
Classifier: Intended Audience :: Science/Research
Classifier: Intended Audience :: Developers
Requires-Python: >=3.11
License-File: LICENSE.txt
Requires-Dist: cython
Dynamic: license-file
